mussels/__init__.py
mussels/__main__.py
mussels/bookshelf.py
mussels/mussels.py
mussels/recipe.py
mussels/tool.py
mussels/utils/__init__.py
mussels/utils/click.py
mussels/utils/versions.py
mussels-0.4.2.dist-info/licenses/LICENSE
mussels-0.4.2.dist-info/METADATA
mussels-0.4.2.dist-info/WHEEL
mussels-0.4.2.dist-info/entry_points.txt
mussels-0.4.2.dist-info/top_level.txt
mussels-0.4.2.dist-info/RECORD
