Metadata-Version: 2.4
Name: mussels
Version: 0.4.2
Summary: Mussels Dependency Build Automation Tool
Home-page: https://github.com/Cisco-Talos/mussels
Author: Micah Snyder
Author-email: micasnyd@cisco.com
Classifier: Programming Language :: Python :: 3
Classifier: License :: OSI Approved :: Apache Software License
Classifier: Operating System :: OS Independent
License-File: LICENSE
Requires-Dist: click>=7.0
Requires-Dist: coloredlogs>=10.0
Requires-Dist: colorama
Requires-Dist: requests
Requires-Dist: patch
Requires-Dist: gitpython
Requires-Dist: pyyaml
Requires-Dist: setuptools
Dynamic: author
Dynamic: author-email
Dynamic: classifier
Dynamic: description
Dynamic: description-content-type
Dynamic: home-page
Dynamic: license-file
Dynamic: requires-dist
Dynamic: summary
